{
    "方剂名称": "光明散",
    "url": "http://zhongyaofangji.com/g/guangmingsan.html",
    "【处方】": "水银5钱，铅锡3钱（1方5钱），枯矾5钱，炒盐5钱，炒消5钱。",
    "【制法】": "上为细末，入于阳城罐内，用铁灯盏盖之，再用铁线扎定，外用旧草鞋烧灰和盐泥固济，用文武火升之，勿令泄气，铁灯盏上常常以水渍之，依法3炷官香时退火，候冷轻手开罐取下灵气雪白，重5钱者为佳，用瓷罐收贮入后炉甘石煅炼听用。羊脑炉甘石1两，用捶熟黄泥包封甘石在内，再将前灵气5分掺于泥上，再用青盐含黄泥捶熟．又裹于外固密，晒干用髻条铁线团团缚定，用炭火煅红，用童便渍之，依法7次，取出去土，将炉甘石研为极细末。",
    "【功能主治】": "目翳。",
    "【用法用量】": "点之立效，或加冰片少许。    翳膜，加硼砂、硇砂各1钱。",
    "【摘录】": "《直指：附遗》卷二十引程东阳方",
    "【拼音名】": "guangmingsan",
    "【注意】": "忌热物。"
}