{
    "方剂名称": "八味丸",
    "url": "http://zhongyaofangji.com/b/baweiwan.html",
    "【处方】": "川巴戟1两半（酒浸，去心，用荔枝肉1两，同炒赤色，去荔枝肉不要），高良姜1两（锉碎，用麦门冬1两半，去心，同炒赤色为度，去门冬），川楝子2两（去核，用降真香1两，锉碎同炒，油出为度，去降真香），吴茱萸1两半（去梗，用青盐1两，同炒后，茱萸炮，同用），胡芦巴1两（用全蝎14个，同炒后，胡芦巴炮，去全蝎不用），山药1两半（用熟地黄同炒焦色，去地黄不用），茯苓1两（用川椒1两，同炒赤色，去椒不用），香附子1两半（去毛，用牡丹皮1两，同炒焦色，去牡丹皮不用）。",
    "【制法】": "上为细末，盐煮，面糊为丸，如梧桐子大。",
    "【功能主治】": "老人常服延寿延年，温平补肝肾，清上实下，分清浊二气，补暖丹田。主积年冷病，累岁沉疴，遗精白浊，赤白带下。",
    "【用法用量】": "每服40-50丸，空心、食前盐汤送下；温酒亦得。",
    "【摘录】": "《寿亲养老》卷四",
    "【别名】": "八物肾气丸、肾气丸、陈氏八味丸"
}