{
    "方剂名称": "凉血五花汤",
    "url": "http://zhongyaofangji.com/l/liangxuewuhuatang.html",
    "【处方】": "红花3至5钱，鸡冠花3至5钱，凌霄花3至5钱，玫瑰花3至5钱，野菊花3至5钱。",
    "【功能主治】": "凉血活血，疏风解毒。主血热发斑，热毒阻络所致盘状红斑性狼疮初期，玫瑰糠疹（风癣）、多形性红斑（血风疮）及一切红斑性皮肤病初期，偏于上半身或全身散在分布者。",
    "【用法用量】": "水煎服。",
    "【备注】": "方中凌霄花凉血活血泻热为主;玫瑰花、红花理气活血化瘀;鸡冠花疏风活血;野菊花清热解毒。本方适用于血热发斑，热毒阻络所引起的皮肤病。因为药味取花，花性轻扬，所以本方以治疗病变在上半身成全身散发者为宜。",
    "【摘录】": "《赵柄南临床经验集》",
    "【各家论述】": "方中凌霄花凉血活血泻热为主，玫瑰花、红花理气活血化瘀，鸡冠花疏风活血，野菊花清热解毒。因为药味取花，花性轻扬，所以本方以治疗病变在上半身或全身散发者为宜。"
}