{
    "方剂名称": "加味补血汤",
    "url": "http://zhongyaofangji.com/j/jiaweibuxuetang.html",
    "【处方】": "当归1两，黄耆1两，荆芥3钱，白术5钱。",
    "【功能主治】": "妇女经水过多，行后复行，面色萎黄，人倦无力。",
    "【用法用量】": "水煎服。",
    "【各家论述】": "古方有补血汤，其方黄耆、当归同用，而黄耆之分量，竟四倍于当归，诚以阴阳互为之根，人之气壮旺者，其血分自易充长，是以此方不以当归为主药，而以黄耆为主药也。用龙眼肉者，因其味甘色赤，多含津液，最能助当归以生血也。用鹿角胶者，因鹿之角原生于头顶督脉之上，督脉为脑髓之来源，故鹿角胶之性善补脑髓。凡脑中血虚者，其脑髓亦必虚，用之以补脑髓，实可与补血之药相助为理也。用丹参、乳香、没药者，因气血虚者，其经络多瘀滞，此于偏枯痿废亦颇有关系，加此通气活血之品，以化其经络之瘀滞，则偏枯痿废者自易愈也。用甘松者，为其能助心房运动有力，以多输血于脑，且又为调养神经之要品，能引诸药至脑以调养其神经也。",
    "【临床应用】": "内风：高某，年过六旬，渐觉两腿乏力，寝至时欲眩仆，神昏健忘，恐成痿废，求为诊治。其脉微弱无力。为制此方服之，连进10剂，两腿较前有力，健忘亦见愈，而仍有眩晕之时。再诊其脉，虽有起色，而仍不任重按，遂于方中加野台参、天门冬各5钱，威灵仙1钱，连服20余剂始愈。",
    "【摘录】": "《辨证录》卷十一"
}