{
    "方剂名称": "回生夺命神丹",
    "url": "http://zhongyaofangji.com/h/huishengduomingshendan.html",
    "【处方】": "羌活3两，白蒺藜3两，藁本3两，天南星3两，防风3两，川续断3两，苍术3两，五加皮3两，独活3两，海风藤3两，白芷3两，大腹皮3两，乌药3两，仙灵脾3两，防已3两，皂角刺3两，川乌3两，明天麻3两，桔梗3两，北细辛3两，柴胡3两，蔓荆子3两，黄芩3两，川萆Z3两，薄荷3两，甘松3两，白芍3两，大黄3两，红花7两，玄参7两，草乌4两，苦参2斤（上用阴阳水各1大桶浸，春5、夏3、秋7、冬9日，煎100沸去滓，加炼蜜1斤，煎成膏如漆），白术2两，胡麻2两，人参（酒浸，蒸熟晒干）2两，砂仁2两，礞石（硝煅）2两，蕤仁（去油）2两，沉香1两，白茯苓1两，木香1两，檀香1两，降香1两，安息香1两，乳香（去油）1两，没药（去油）1两，川芎1两，牛膝1两，红花1两，香蛇（酒浸，焙干）1两，血竭1两，白僵蚕1两，松脂（煮去苦水）1两，云母石1两，冰片1两，鹅管石1两，磁石1两，肉苁蓉1两，原蚕蛾1两，桑螵蛸1两，蟾酥5钱，麝香5钱，人牙（炙黄色）5个，白花蛇1条（酒浸，去皮，晒干）。",
    "【制法】": "上为末，用前药膏共为丸，如弹子大，朱砂为衣，金箔包裹。",
    "【功能主治】": "三十六疯，十四癞。",
    "【用法用量】": "年深久远者，每服10丸；4-5年者，每服4-5丸；1-2年者，每服1-2丸，须麻姑酒磨下。随汗愈。",
    "【摘录】": "《疡医大全》卷二十八"
}