{
    "方剂名称": "明目地黄丸",
    "url": "http://zhongyaofangji.com/m/mingmudihuangwan.html",
    "【处方】": "熟地240克 茯苓 牡丹皮（酒炒）各90克 泽泻（盐酒炒）90克 怀山药（炒）120克 山茱萸肉（酒炒）120克 白芍药（炒）白菊花 当归 枸杞子 白蒺藜（炒）各90克 石决明120克",
    "【性状】": "为黑褐色至黑色的水蜜丸、黑色的小蜜丸或大蜜丸；气微香，味先甜而后苦、涩。",
    "【炮制】": "上十二味，粉碎成细粉，过筛，混匀。每100g粉末用炼蜜35～50g加适量的水泛丸，干燥，制成水蜜丸；或加炼蜜90～110g制成小蜜丸或大蜜丸，即得。",
    "【功能主治】": "治视物模糊，目涩羞明。",
    "【用法用量】": "每服9克，淡盐汤送服。",
    "【规格】": "大蜜丸每丸重9g",
    "【贮藏】": "密封。",
    "【摘录】": "《全国中药成药处方集》（上海方）",
    "【制法】": "共研细粉，炼蜜为丸，如梧桐子大。",
    "【注意】": "服药期间忌食萝卜。",
    "【备注】": "方中熟地、萸肉补肾养肝；山药补脾益真阴；丹皮凉血退阴火，当归、川芎养血活血；茯苓、泽泻渗利湿热；麦冬、石斛滋阴润燥。配合成方，共奏补肾滋阴，养肝明目之功。"
}