{
    "方剂名称": "狗皮膏",
    "url": "http://zhongyaofangji.com/g/goupigao.html",
    "【处方】": "乳香5钱，没药5钱，木鳖子10个，杏仁49个，桃枝49节（二指长），柳枝49节（如箸大）。",
    "【性状】": "为摊于兽皮或布上的黑膏药。",
    "【炮制】": "上二十九味，乳香、没药、丁香、肉桂分别粉碎成粉末，与樟脑、冰片粉末配研，过筛，混匀；其余生川乌等二十三味酌予碎断，与食用植物油3495g同置锅内炸枯，去渣，滤过，炼至滴水成珠。另取红丹1040～1140g，加入油内，搅匀，收膏，将膏浸泡于水中。取膏，用文火熔化，加入上述粉末，搅匀，分摊于兽皮或布上，即得。",
    "【功能主治】": "泻痢。",
    "【用法用量】": "《良朋汇集》：兼可作封肚暖脐膏。",
    "【注意】": "孕妇勿贴。",
    "【规格】": "每张净重（1）12g（2）15g（3）24g（4）30g",
    "【贮藏】": "密闭，置阴凉干燥处。",
    "【摘录】": "《回春》卷三",
    "【制法】": "上用香油7两，将木鳖子以下4味入油炸浮；捞取滓；下好黄丹（飞过）3两，熬；将成膏，用槐枝不住手搅，滴水成珠，退火；再入乳香、没药，加麝香1分搅匀；退火毒，以狗皮摊膏。",
    "【别名】": "麝香狗皮膏"
}