{
    "方剂名称": "调气养神汤",
    "url": "http://zhongyaofangji.com/d/diaoqiyangshentang.html",
    "【处方】": "龙眼肉8钱，柏子仁5钱，生龙骨（捣碎）5钱，生牡蛎（捣碎）5钱，远志（不炙）2钱，生地黄6钱，天门冬4钱，甘松2钱，生麦芽3钱，菖蒲2钱，甘草1钱半，镜面朱砂（研细，用头次煎药汤2次送服）3分。",
    "【功能主治】": "养神明，滋心血，理肝气，清虚热。主其人思虑过度，伤其神明，或更因思虑过度，暗生内热，其心肝之血，消耗日甚，以致心火肝气，上冲头部，扰乱神经，致神经失其所司，知觉错乱，以是为非，以非为是，而不致于疯狂过甚者。",
    "【用法用量】": "磨取铁锈浓水煎药。",
    "【备注】": "此乃养神明，滋心血，理肝气，清虚热之方也。龙眼肉色赤人心，且多津液，最能滋补血分，兼能保和心气之耗散，故以之为主药。柏子仁善养肝，兼能镇肝（水能养木，兼能镇木），又与龙骨、牡蛎之善于敛戢肝火、肝气者同用，则肝火、肝气自然不挟心火上升，以扰乱神经。用生地黄者，取其能泻上焦之虚热，更能助龙眼肉生血。用天门冬者，取其凉润之性，能清心宁棹，即以开燥痰。用远志、菖蒲者，取共能开心窍，利痰涎，且能通神明。用朱砂、铁锈水者，以共皆能镇安神经，又能定心平肝。用生麦芽者，诚以肝为将军之官，中寄相火，若但知敛之镇之，或激动共反应之力，故又加生麦芽，以将顺其性。盖麦芽炒用能消食，生用则替舒肝气。至子甘松，中医用之以清热、开瘀，逐痹；西医则推为安养神经之妙药，而兼能治霍乱转筋。盖神经不失其所司，则筋可不转，此亦足见安养神经之效。",
    "【摘录】": "《衷中参西》上册",
    "【各家论述】": "龙眼肉色赤入心，且多津液，最能滋补血分，兼能保和心气之耗散，故以之为主药；柏树杪向西北，禀金水之精气，其实采于仲冬，饱受霜露，且多含油质，故善养肝，兼能镇肝（水能养木，金能镇木），又与龙骨，牡蛎之善于敛戢肝火、肝气者同用，则肝火肝气自不挟心火上升，以扰乱神经也；用生地黄者，取其能泻上焦之虚热，更能助龙眼肉生血也；用天门冬者，取其凉润之性，能清心宁神，即以开燥痰也；用远志、菖蒲者，取其能开心窍，利痰涎，且能通神明也；用朱砂、铁锈水者，以其皆能镇安神经，又能定心平肝也；用生麦芽者，诚以肝为将军之官，中寄相火，若但知敏之镇之，或激动其反应之力，故又加生麦芽，以将顺其性，盖麦芽炒用能消食，生用则善舒肝气也。至于甘松，用之以清热、开瘀、逐痹，兼有安养神经之效。"
}