{
    "方剂名称": "赤霆救疫夺命丹",
    "url": "http://zhongyaofangji.com/c/chitingjiuyiduomingdan.html",
    "【处方】": "真水安息香（即龙涎香）6分，廉珠粉1分，西牛黄1分，当门子5分，梅花、冰片5分，净硼砂2钱，明雄黄2钱（用马牙火消1钱2分，用熔银罐同煅炼，和凝成丹），飞净辰砂2钱，明矾2钱（生用），真血珀1钱，生玳瑁屑2钱，猪牙皂角末1钱，川郁金2钱，赤金箔9张，公丁香1钱，广木香1钱，乌沉香1钱，白檀香1钱。",
    "【制法】": "勿见火。此丹药贵重，瓷器珍藏，慎勿泄气。",
    "【功能主治】": "淬暴中恶，闷痧臭毒，霍乱吐泻，脉厥脉伏，转筋入腹，绞肠钓脚，魄汗淋漓，气闭形脱，甚至舌冷囊缩，妇人乳头缩，手指螺瘪，以及小儿惊风、癫病、邪崇痰塞、痉厥，老年中风、中，山岚瘴疬，诸暴危笃急证，呼唤不醒，手足鼻舌已冷，牙关紧闭。",
    "【用法用量】": "急将此丹少许，至多不过1分，浮于冷茶水面，从容灌入。自然追邪外出，俾得醒回，厥转寒去，脉起，以便延医诊治。",
    "【注意】": "孕妇忌服。",
    "【摘录】": "《经验各种秘方辑要》"
}