{
    "方剂名称": "里东丸",
    "url": "http://zhongyaofangji.com/l/lidongwan.html",
    "【处方】": "五灵脂（炒酱色为度）9两5钱5分，番木鳖（用麻油在铜杓内煎滚，放在内约二沉二浮即好）10两，穿山甲（炒黄焦）2两5钱，地龙（韭地者佳，将滚汤泡熟，在日内晒干，如不干，在火上焙干，不得隔夜）9两5钱，黄麻灰（切碎，贮阳城罐内，盐泥封固头，大火内煅）3两，麝香3钱3分，芸香（即白胶香，枫脂也）2两5钱，乳香（去油）1两2钱5分，古文五珠钱（火煅）17个，自然铜（火煅红，醋淬）2两，草乌（去皮尖，炒）3钱5分，全蝎（去尾上钩）1两2钱5分，当归（酒洗）1两2钱5，京墨（如方氏，陈者佳，火烧烟尽为度）2钱5分。",
    "【制法】": "上为末，酒糊为丸，朱砂为衣，每丸重1钱5分，蜡丸（永久不坏）。",
    "【功能主治】": "折伤。",
    "【用法用量】": "好酒化开，清晨先略饮食后服下；下部伤亦食后服。",
    "【各家论述】": "是方五灵脂入肝经，用以利气行血，退肿接骨；番木鳖用以解破处之血热，消形伤之肿结，穿山甲用以出阴入阳，走窜经络，迅达伤处；蚯蚓用以从阳入阴，取蚓毒攻络内之瘀，更取蚓性逐水解热消肿、四者功专外消结肿，分两独重者，治伤纲领之药也。黄麻灰用以破血利小便，行伤接骨；麝香通关入肾，用以外通百窍，内透骨髓；乳香入心，用以托里定痛；芸香性燥入脾，用以胜肉理之湿，排脓止痛，强筋骨，生肌肉；古文钱跌扑损伤者用半两五珠，以腐蚀坏肉；自然铜性燥破血，用以逐败恶之血，六者去瘀生新，安神定痛，分两次之者，治伤之条目也。草乌用以祛经络之风，从表而出；全蝎用以直攻破损之处，消散内风；当归补营血，用以去瘀生新；京墨灰涩能固卫气，用以生肌肤，合伤缝。统论全方，虽非控经定证，然其调折伤之法井井有条，先退肿，后定痛，腐其坏肉，祛其恶血，散其风，活其血，俾经脉流通，则气血调畅，脂膏流着于伤处，其骨自接也。",
    "【摘录】": "《古方选注》卷下引少陵僧方"
}